{"name":"Ondetemjogo","tagline":"Plataforma \"Onde Tem Jogo?\"","body":"### Bem vindo ao projeto \"Onde Tem Jogo?\"\r\nO projeto \"Onde Tem Jogo?\" é uma plataforma que auxilia na busca de jogos do seu time favorito em bares/lanchonetes. Enquanto os usuários podem encontrar o melhor horário e local para se reunir os donos de estabelecimento podem utilizar a plataforma para divulgação de suas marcas atingindo uma infinidade de clientes em potencial.\r\n\r\nEm resumo desejamos criar conexões!\r\ncolocando as pessoas certas nos lugares certos em um momento específico de suas vidas.\r\n\r\n\r\n","google":"","note":"Don't delete this file! It's used internally to help with page regeneration."}